{
    "configurations": [
        {
            "name": "Jetson Orin Nano",
            "includePath": [
                "${workspaceFolder}/**",
                "/usr/local/cuda/include",
                "/usr/include/aarch64-linux-gnu",
                "/opt/nvidia/vpi3/include",
                "/usr/include/opencv4",
                "/opt/nvidia/deepstream/deepstream/sources/includes",
                "/usr/src/jetson_multimedia_api/include"
            ],
            "defines": [
                "JETSON_ORIN",
                "VESPA_DEBUG"
            ],
            "compilerPath": "/usr/bin/gcc",
            "cStandard": "c17",
            "cppStandard": "c++17",
            "intelliSenseMode": "linux-gcc-arm64"
        }
    ],
    "version": 4
}